LICENSE
MANIFEST.in
README.md
RELEASE-VERSION
setup.py
version.py
dossier/__init__.py
dossier.models.egg-info/PKG-INFO
dossier.models.egg-info/SOURCES.txt
dossier.models.egg-info/dependency_links.txt
dossier.models.egg-info/entry_points.txt
dossier.models.egg-info/not-zip-safe
dossier.models.egg-info/requires.txt
dossier.models.egg-info/top_level.txt
dossier/models/__init__.py
dossier/models/etl.py
dossier/models/pairwise.py
dossier/models/query.py
dossier/models/report.py
dossier/models/soft_selectors.py
dossier/models/subtopic.py
dossier/models/features/__init__.py
dossier/models/features/basic.py
dossier/models/features/sip.py
dossier/models/features/stopwords.py
dossier/models/tests/__init__.py
dossier/models/tests/test_features.py
dossier/models/tests/test_pairwise.py
dossier/models/tests/test_soft_selectors.py
dossier/models/tests/test_web.py
dossier/models/web/__init__.py
dossier/models/web/__main__.py
dossier/models/web/run.py
dossier/models/web/wsgi.py
dossier/models/web/static/SortingDesk.js
dossier/models/web/static/api-sorting_desk-live.js
dossier/models/web/static/sorting_desk-live.js
dossier/models/web/static/theme-sorting_desk-default.css
dossier/models/web/static/lib/jquery-2.1.1.min.js
dossier/models/web/static/lib/require-2.1.14.min.js
dossier/models/web/static/tpl/example-sortingdesk.html
dossier/models/web/static/tpl/example-sortingqueue.html