Metadata-Version: 1.1
Name: dossier.models
Version: 0.6.2
Summary: Active learning models
Home-page: http://github.com/dossier/dossier.models
Author: Diffeo, Inc.
Author-email: support@diffeo.com
License: MIT
Platform: UNKNOWN
Classifier: Development Status :: 3 - Alpha
Classifier: Topic :: Utilities
Classifier: License :: OSI Approved :: MIT License
